nudenet/__init__.py
nudenet/classifier.py
nudenet/detector.py
nudenet/detector_utils.py
nudenet/image_utils.py
nudenet/lite_classifier.py
nudenet/video_utils.py
VNudeNet-2.1.0.dist-info/LICENSE
VNudeNet-2.1.0.dist-info/METADATA
VNudeNet-2.1.0.dist-info/WHEEL
VNudeNet-2.1.0.dist-info/top_level.txt
VNudeNet-2.1.0.dist-info/RECORD
