Metadata-Version: 2.1
Name: VNudeNet
Version: 2.1.0
Summary: An ensemble of Neural Nets for Nudity Detection and Censoring
Home-page: https://github.com/bedapudi6788/NudeNet
Author: BEDAPUDI PRANEETH
Author-email: praneethbedapudi@gmail.com
License: GPLv3
Platform: UNKNOWN
Classifier: License :: OSI Approved :: GNU General Public License v3 (GPLv3)
Classifier: Programming Language :: Python
Classifier: Programming Language :: Python :: 3
Classifier: Programming Language :: Python :: 3.6
Classifier: Programming Language :: Python :: Implementation :: CPython
Classifier: Programming Language :: Python :: Implementation :: PyPy
Requires-Python: >=3.6.0
Requires-Dist: pillow
Requires-Dist: opencv-python-headless (>=4.5.1.48)
Requires-Dist: pydload
Requires-Dist: scikit-image
Requires-Dist: onnxruntime-gpu
